LICENSE
MANIFEST.in
README.rst
setup.py
django_noticebox.egg-info/PKG-INFO
django_noticebox.egg-info/SOURCES.txt
django_noticebox.egg-info/dependency_links.txt
django_noticebox.egg-info/not-zip-safe
django_noticebox.egg-info/top_level.txt
noticebox/__init__.py
noticebox/context_processors.py
noticebox/handlers.py
noticebox/managers.py
noticebox/models.py
noticebox/urls.py
noticebox/views.py
noticebox/templates/noticebox/base.html
noticebox/templates/noticebox/notice_detail.html
noticebox/templates/noticebox/notice_list.html
noticebox/templates/noticebox/default/email_body.txt
noticebox/templates/noticebox/default/email_subject.txt
noticebox/templates/noticebox/default/web_body.html
noticebox/templates/noticebox/default/web_subject.html
noticebox/tests/__init__.py
noticebox/tests/base.py
noticebox/tests/settings.py
noticebox/tests/test_context_processors.py
noticebox/tests/test_handlers.py
noticebox/tests/test_simple.py
noticebox/tests/test_views.py
noticebox/tests/urls.py
noticebox/tests/templates/noticebox/hello/email_body.txt
noticebox/tests/templates/noticebox/hello/email_subject.txt
noticebox/tests/templates/noticebox/hello/web_body.html
noticebox/tests/templates/noticebox/hello/web_subject.html