Metadata-Version: 1.1
Name: django-noticebox
Version: 0.2
Summary: Django-noticebox is a reusable Django application which provides functionality for sending notices to site users. The notices can be displayed when user signs in, sent by email or both.
Home-page: http://github.com/mila/django-noticebox/tree/master
Author: Miloslav Pojman
Author-email: miloslav.pojman@gmail.com
License: UNKNOWN
Platform: UNKNOWN
Classifier: Environment :: Web Environment
Classifier: Intended Audience :: Developers
Classifier: License :: OSI Approved :: BSD License
Classifier: Operating System :: OS Independent
Classifier: Programming Language :: Python
Classifier: Framework :: Django
